google/cloud/websecurityscanner/__init__.py
google/cloud/websecurityscanner/gapic_version.py
google/cloud/websecurityscanner/py.typed
google/cloud/websecurityscanner_v1/__init__.py
google/cloud/websecurityscanner_v1/gapic_metadata.json
google/cloud/websecurityscanner_v1/gapic_version.py
google/cloud/websecurityscanner_v1/py.typed
google/cloud/websecurityscanner_v1/services/__init__.py
google/cloud/websecurityscanner_v1/services/web_security_scanner/__init__.py
google/cloud/websecurityscanner_v1/services/web_security_scanner/async_client.py
google/cloud/websecurityscanner_v1/services/web_security_scanner/client.py
google/cloud/websecurityscanner_v1/services/web_security_scanner/pagers.py
google/cloud/websecurityscanner_v1/services/web_security_scanner/transports/__init__.py
google/cloud/websecurityscanner_v1/services/web_security_scanner/transports/base.py
google/cloud/websecurityscanner_v1/services/web_security_scanner/transports/grpc.py
google/cloud/websecurityscanner_v1/services/web_security_scanner/transports/grpc_asyncio.py
google/cloud/websecurityscanner_v1/services/web_security_scanner/transports/rest.py
google/cloud/websecurityscanner_v1/services/web_security_scanner/transports/rest_base.py
google/cloud/websecurityscanner_v1/types/__init__.py
google/cloud/websecurityscanner_v1/types/crawled_url.py
google/cloud/websecurityscanner_v1/types/finding.py
google/cloud/websecurityscanner_v1/types/finding_addon.py
google/cloud/websecurityscanner_v1/types/finding_type_stats.py
google/cloud/websecurityscanner_v1/types/scan_config.py
google/cloud/websecurityscanner_v1/types/scan_config_error.py
google/cloud/websecurityscanner_v1/types/scan_run.py
google/cloud/websecurityscanner_v1/types/scan_run_error_trace.py
google/cloud/websecurityscanner_v1/types/scan_run_log.py
google/cloud/websecurityscanner_v1/types/scan_run_warning_trace.py
google/cloud/websecurityscanner_v1/types/web_security_scanner.py
google/cloud/websecurityscanner_v1alpha/__init__.py
google_cloud_websecurityscanner-1.19.0.dist-info/licenses/LICENSE
google_cloud_websecurityscanner-1.19.0.dist-info/METADATA
google_cloud_websecurityscanner-1.19.0.dist-info/WHEEL
google_cloud_websecurityscanner-1.19.0.dist-info/top_level.txt
google_cloud_websecurityscanner-1.19.0.dist-info/RECORD
